unred/__init__.py
unred/unred.py
unred-0.1.2.data/scripts/unred_stars.py
unred-0.1.2.dist-info/METADATA
unred-0.1.2.dist-info/RECORD
unred-0.1.2.dist-info/WHEEL
unred-0.1.2.dist-info/top_level.txt
