Metadata-Version: 2.1
Name: unred
Version: 0.1.2
Summary: Determine the interstellar extinction for observed stars
Home-page: https://github.com/pbrus/unredden-stars
Author: Przemysław Bruś
License: UNKNOWN
Keywords: reddening,extinction,stars
Platform: UNKNOWN
Classifier: Development Status :: 5 - Production/Stable
Classifier: Intended Audience :: Science/Research
Classifier: License :: OSI Approved :: MIT License
Classifier: Operating System :: OS Independent
Classifier: Programming Language :: Python
Classifier: Programming Language :: Python :: 3.5
Classifier: Programming Language :: Python :: 3.6
Classifier: Programming Language :: Python :: 3.7
Classifier: Topic :: Scientific/Engineering :: Astronomy
Classifier: Topic :: Utilities
Requires-Dist: numpy
Requires-Dist: scipy
